helix/__init__.py
helix/amino_acids.py
helix/api.py
helix/bioinformatics.py
helix/cli.py
helix/codon.py
helix/cyclospectrum.py
helix/nussinov_algorithm.py
helix/protein.py
helix/triage.py
helix/workflows.py
helix/crispr/__init__.py
helix/crispr/dag_api.py
helix/crispr/guide.py
helix/crispr/model.py
helix/crispr/pam.py
helix/crispr/rules.py
helix/crispr/score.py
helix/crispr/simulate.py
helix/crispr/simulator.py
helix/datasets/__init__.py
helix/datasets/__pycache__/__init__.cpython-313.pyc
helix/datasets/dna/human.txt
helix/datasets/dna/plasmid_demo.fna
helix/datasets/protein/demo_protein.faa
helix/edit/__init__.py
helix/edit/dag.py
helix/edit/events.py
helix/edit/physics.py
helix/edit/simulate.py
helix/genome/__init__.py
helix/genome/diff.py
helix/genome/digital.py
helix/graphs/__init__.py
helix/graphs/colored.py
helix/graphs/dbg.py
helix/io/__init__.py
helix/motif/__init__.py
helix/motif/core.py
helix/motif/em.py
helix/motif/online.py
helix/motif/steme.py
helix/prime/__init__.py
helix/prime/dag_api.py
helix/prime/design.py
helix/prime/edit_spec.py
helix/prime/model.py
helix/prime/rules.py
helix/prime/simulate.py
helix/prime/simulator.py
helix/rna/__init__.py
helix/rna/mfe.py
helix/rna/params.py
helix/rna/partition.py
helix/schema/__init__.py
helix/schema/spec_manifest.json
helix/seed/__init__.py
helix/seed/extend.py
helix/seed/minimizer.py
helix/seed/syncmer.py
helix/sketch/__init__.py
helix/sketch/distance.py
helix/sketch/hll.py
helix/sketch/minhash.py
helix/string/__init__.py
helix/string/edit.py
helix/string/fm.py
helix/visualization/__init__.py
helix/visualization/dag_viz.py
helix/visualization/diff_view.py
helix/viz/__init__.py
helix/viz/_utils.py
helix/viz/alignment.py
helix/viz/crispr_track.py
helix/viz/distance.py
helix/viz/minimizers.py
helix/viz/motif.py
helix/viz/prime_track.py
helix/viz/rna.py
helix/viz/seed.py
helix/viz/seed_chain.py
veri_helix-0.3.0.dist-info/METADATA
veri_helix-0.3.0.dist-info/WHEEL
veri_helix-0.3.0.dist-info/entry_points.txt
veri_helix-0.3.0.dist-info/top_level.txt
veri_helix-0.3.0.dist-info/RECORD
