Metadata-Version: 2.4
Name: veri-helix
Version: 0.3.0
Summary: Friendly, reproducible bioinformatics toolkit with schema-verified viz
Author: Helix Authors
License-Expression: Apache-2.0
Project-URL: Homepage, https://github.com/omniscoder/Helix
Project-URL: Documentation, https://omniscoder.github.io/Helix/
Project-URL: Issues, https://github.com/omniscoder/Helix/issues
Keywords: bioinformatics,genomics,rna,alignment,visualization
Classifier: Programming Language :: Python :: 3
Classifier: Topic :: Scientific/Engineering :: Bio-Informatics
Classifier: Intended Audience :: Science/Research
Requires-Python: >=3.10
Requires-Dist: numpy>=1.24
Requires-Dist: pyyaml>=6.0
Provides-Extra: viz
Requires-Dist: matplotlib>=3.6; extra == "viz"
Provides-Extra: protein
Requires-Dist: biopython>=1.84; extra == "protein"
Provides-Extra: schema
Requires-Dist: pydantic>=2.5; extra == "schema"
Provides-Extra: dev
Requires-Dist: pytest; extra == "dev"
Requires-Dist: pytest-cov; extra == "dev"
Requires-Dist: ruff; extra == "dev"
Requires-Dist: mypy; extra == "dev"
Requires-Dist: build; extra == "dev"
Requires-Dist: twine; extra == "dev"
Requires-Dist: matplotlib>=3.6; extra == "dev"
Requires-Dist: biopython>=1.84; extra == "dev"
Requires-Dist: pydantic>=2.5; extra == "dev"
Requires-Dist: psutil>=5.9; extra == "dev"
